keyboardsounds/__init__.py
keyboardsounds/app_detector.py
keyboardsounds/app_rules.py
keyboardsounds/audio_manager.py
keyboardsounds/daemon.py
keyboardsounds/daemon_manager.py
keyboardsounds/listener.py
keyboardsounds/main.py
keyboardsounds/path_resolver.py
keyboardsounds/profile.py
keyboardsounds/profile_builder.py
keyboardsounds/profile_validation.py
keyboardsounds/root.py
keyboardsounds/external_api/__connection_handler.py
keyboardsounds/external_api/__external_api.py
keyboardsounds/external_api/__init__.py
keyboardsounds/profiles/profile.template.yaml
keyboardsounds/profiles/alpaca/LICENSE
keyboardsounds/profiles/alpaca/press_back.mp3
keyboardsounds/profiles/alpaca/press_enter.mp3
keyboardsounds/profiles/alpaca/press_key1.mp3
keyboardsounds/profiles/alpaca/press_key2.mp3
keyboardsounds/profiles/alpaca/press_key3.mp3
keyboardsounds/profiles/alpaca/press_key4.mp3
keyboardsounds/profiles/alpaca/press_key5.mp3
keyboardsounds/profiles/alpaca/press_space.mp3
keyboardsounds/profiles/alpaca/profile.yaml
keyboardsounds/profiles/alpaca/release_back.mp3
keyboardsounds/profiles/alpaca/release_enter.mp3
keyboardsounds/profiles/alpaca/release_key.mp3
keyboardsounds/profiles/alpaca/release_space.mp3
keyboardsounds/profiles/apex-pro-tkl-v2/enter.wav
keyboardsounds/profiles/apex-pro-tkl-v2/key1.wav
keyboardsounds/profiles/apex-pro-tkl-v2/key3.wav
keyboardsounds/profiles/apex-pro-tkl-v2/key4.wav
keyboardsounds/profiles/apex-pro-tkl-v2/profile.yaml
keyboardsounds/profiles/apex-pro-tkl-v2/space.wav
keyboardsounds/profiles/banana-split/banana-l-1.wav
keyboardsounds/profiles/banana-split/banana-l-2.wav
keyboardsounds/profiles/banana-split/banana-l-3.wav
keyboardsounds/profiles/banana-split/banana-l-4.wav
keyboardsounds/profiles/banana-split/banana-l-5.wav
keyboardsounds/profiles/banana-split/banana-l-6.wav
keyboardsounds/profiles/banana-split/banana-l-7.wav
keyboardsounds/profiles/banana-split/profile.yaml
keyboardsounds/profiles/g502x-wireless/middle.wav
keyboardsounds-6.4.1.dist-info/licenses/LICENSE
keyboardsounds-6.4.1.dist-info/METADATA
keyboardsounds-6.4.1.dist-info/WHEEL
keyboardsounds-6.4.1.dist-info/entry_points.txt
keyboardsounds-6.4.1.dist-info/top_level.txt
keyboardsounds-6.4.1.dist-info/RECORD
