Metadata-Version: 2.4
Name: keyboardsounds
Version: 6.4.1
Summary: Adds the ability to play sounds while typing on any system.
Author: Nathan Fiscaletti
Author-email: Nathan Fiscaletti <nate.fiscaletti@gmail.com>
Project-URL: Homepage, https://github.com/nathan-fiscaletti/keyboardsounds
Classifier: Programming Language :: Python :: 3
Classifier: License :: OSI Approved :: MIT License
Classifier: Operating System :: OS Independent
Requires-Python: >=3.7
License-File: LICENSE
Requires-Dist: pygame==2.6.1
Requires-Dist: pynput==1.8.1
Requires-Dist: psutil==6.1.0
Requires-Dist: imageio-ffmpeg==0.5.1
Requires-Dist: pyyaml==6.0.2
Requires-Dist: setuptools==75.3.0
Requires-Dist: requests==2.32.3
Requires-Dist: pydub==0.25.1
Requires-Dist: audioop-lts==0.2.2; python_version >= "3.13"
Requires-Dist: pyinstaller==6.16.0
Requires-Dist: libevdev==0.13.1; sys_platform == "linux"
Dynamic: author
Dynamic: license-file
